jsonrpc_python_client_generator/__init__.py
jsonrpc_python_client_generator/client.py
jsonrpc_python_client_generator/generator.py
jsonrpc_python_client_generator/response.py
jsonrpc_python_client_generator-1.0.3.dist-info/LICENSE
jsonrpc_python_client_generator-1.0.3.dist-info/METADATA
jsonrpc_python_client_generator-1.0.3.dist-info/WHEEL
jsonrpc_python_client_generator-1.0.3.dist-info/top_level.txt
jsonrpc_python_client_generator-1.0.3.dist-info/RECORD
