Metadata-Version: 2.1
Name: jsonrpc_python_client_generator
Version: 1.0.3
Summary: Jsonrpc Python Client Generator
Home-page: https://github.com/vk1511work/jsonrpc-python-client-generator
Author: vk1511work
Author-email: vk1511work@gmail.com
Keywords: jsonrpc 2.0 python client generator
Classifier: Programming Language :: Python :: 3.10
Classifier: License :: OSI Approved :: MIT License
Classifier: Operating System :: OS Independent
Requires-Python: >=3.10
License-File: LICENSE
Requires-Dist: requests >=2.25.1
